py48/__init__.py
py48/parser.py
py48/절입데이터.csv
py48-1.3.dist-info/METADATA
py48-1.3.dist-info/WHEEL
py48-1.3.dist-info/top_level.txt
py48-1.3.dist-info/RECORD
